pandoc_secnos.py
pandoc_secnos-2.2.2.dist-info/AUTHORS
pandoc_secnos-2.2.2.dist-info/LICENSE
pandoc_secnos-2.2.2.dist-info/METADATA
pandoc_secnos-2.2.2.dist-info/WHEEL
pandoc_secnos-2.2.2.dist-info/entry_points.txt
pandoc_secnos-2.2.2.dist-info/top_level.txt
pandoc_secnos-2.2.2.dist-info/RECORD
