Metadata-Version: 2.1
Name: pandoc-secnos
Version: 2.2.2
Summary: Equation number filter for pandoc
Home-page: https://github.com/tomduck/pandoc-secnos
Author: Thomas J. Duck
Author-email: tomduck@tomduck.ca
License: GPL
Download-URL: https://github.com/tomduck/pandoc-secnos/tarball/2.2.2
Keywords: pandoc equation numbers filter
Platform: UNKNOWN
Classifier: Development Status :: 4 - Beta
Classifier: Intended Audience :: End Users/Desktop
Classifier: Environment :: Console
Classifier: License :: OSI Approved :: GNU General Public License v3 (GPLv3)
Classifier: Programming Language :: Python
Requires-Dist: pandoc-xnos (<3.0,>=2.4.2)
